README.md
setup.py
fbones/__init__.py
fbones/fbones.py
fbones.egg-info/PKG-INFO
fbones.egg-info/SOURCES.txt
fbones.egg-info/dependency_links.txt
fbones.egg-info/entry_points.txt
fbones.egg-info/not-zip-safe
fbones.egg-info/requires.txt
fbones.egg-info/top_level.txt