Metadata-Version: 1.0
Name: fbones
Version: 0.0.6
Summary: A bootstrap toolkit to kickoff a flask project
Home-page: https://github.com/ipconfiger/fbones
Author: Alexander.Li
Author-email: superpowerlee@gmail.com
License: GNU GENERAL PUBLIC LICENSE
Platform: UNKNOWN
